sparkleframe/__init__.py
sparkleframe/activate.py
sparkleframe/conftest.py
sparkleframe/context.py
sparkleframe/engine.py
sparkleframe/gpt_utils.py
sparkleframe/version.txt
sparkleframe/base/__init__.py
sparkleframe/base/dataframe.py
sparkleframe/polarsdf/__init__.py
sparkleframe/polarsdf/column.py
sparkleframe/polarsdf/column_test.py
sparkleframe/polarsdf/dataframe.py
sparkleframe/polarsdf/dataframe_test.py
sparkleframe/polarsdf/functions.py
sparkleframe/polarsdf/functions_test.py
sparkleframe/polarsdf/functions_utils.py
sparkleframe/polarsdf/functions_utils_test.py
sparkleframe/polarsdf/group.py
sparkleframe/polarsdf/session.py
sparkleframe/polarsdf/session_test.py
sparkleframe/polarsdf/types.py
sparkleframe/polarsdf/types_test.py
sparkleframe/polarsdf/types_utils.py
sparkleframe/polarsdf/types_utils_test.py
sparkleframe/polarsdf/window.py
sparkleframe/polarsdf/window_test.py
sparkleframe/tests/__init__.py
sparkleframe/tests/pyspark_test.py
sparkleframe/tests/spark.py
sparkleframe/tests/sparkle.py
sparkleframe/tests/utils.py
sparkleframe-0.5.0.dist-info/licenses/LICENSE
sparkleframe-0.5.0.dist-info/WHEEL
sparkleframe-0.5.0.dist-info/METADATA
sparkleframe-0.5.0.dist-info/RECORD
