Metadata-Version: 2.4
Name: sparkleframe
Version: 0.5.0
Summary: Sparkleframe
Author-email: Jose Helio de Brum Muller <josemuller.flypipe@gmail.com>
Requires-Python: >=3.8
Classifier: Development Status :: 3 - Alpha
Classifier: Intended Audience :: Developers
Classifier: Intended Audience :: Information Technology
Classifier: License :: OSI Approved :: Apache Software License
Classifier: Programming Language :: Python :: 3
License-File: LICENSE
Requires-Dist: polars >=1.30
Project-URL: Home, https://github.com/flypipe/sparkleframe.git
